{
  "fixture name":           "body name,           density,  friction, isSensor, restitution,  categoryBits, groupIndex, maskBits, shape type, vertices,                                                                           sprite size,  sprite offset x,  sprite offset y,  draw_type,                  line width, line red, line green, line blue,  body offset x,  body offset y,  texture name",

  "ground main":            "[\"ground\",         1,        10,       0,        0,            1,            0,          65535,    \"box\",    \"[100, 20]\",                                                                      0,            0,                0,                \"texture\",                2.5,        1.0,      0,          0,          0,              0,              \"ground\"]", 
  "ground post 1":          "[\"ground\",         1,        0.1,      0,        0,            1,            0,          65535,    \"box\",    \"[2, 4]\",                                                                         0,            0,                0,                \"texture\",                2.5,        1.0,      0,          0,          -45,            12,             \"body\"]", 
  "ground post 2":          "[\"ground\",         1,        0.1,      0,        0,            1,            0,          65535,    \"box\",    \"[2, 4]\",                                                                         0,            0,                0,                \"texture\",                2.5,        1.0,      0,          0,          45,             12,             \"body\"]",
  "body":                   "[\"body\",           0.1,      0.1,      0,        0.5,          1,            0,          65535,    \"box\",    \"[2, 2]\",                                                                         0,            0,                0,                \"line loop\",              2.5,        1.0,      0,          0,          0,              0,              \"body\"]",
  "bucket main":            "[\"bucket\",         1,        0.1,      0,        0,            1,            0,          65535,    \"chain\",  \"[-12, 12, -5, 0, 5, 0, 12, 12]\",                                                 0,            0,                0,                \"line strip\",             2.5,        1.0,      0.0,        0.0,        0,              0,              \"\"]",
  "bucket under box 1":     "[\"bucket\",         1,        0.1,      0,        0,            1,            0,          65535,    \"box\",    \"[0.5, 4]\",                                                                       0,            0,                0,                \"texture\",                2.5,        1.0,      0,          0,          -2.5,           -2,             \"body\"]",
  "bucket under box 2":     "[\"bucket\",         1,        0.1,      0,        0,            1,            0,          65535,    \"box\",    \"[0.5, 4]\",                                                                       0,            0,                0,                \"texture\",                2.5,        1.0,      0,          0,          2.5,            -2,             \"body\"]",
  "bucket under box 3":     "[\"bucket\",         100,      0.1,      0,        0,            1,            0,          65535,    \"box\",    \"[6, 1]\",                                                                         0,            0,                0,                \"texture\",                2.5,        1.0,      0,          0,          0,              -4,             \"body\"]",
  "bucket ball":            "[\"bucket ball\",    1,        0.1,      0,        0,            1,            0,          65535,    \"circle\", \"[1.5]\",                                                                          0,            0,                0,                \"texture\",                2.5,        1.0,      0,          0,          0,              0,              \"bucket ball\"]",
  "boat":                   "[\"boat\",           0.8,      0.1,      0,        0.5,          1,            0,          65535,    \"sprite\", \"[1.42, 1.36, -1.83, 0.78, -2.53, -1.08, 4.61, -1.02, 6.29, 0.02]\",               8.76,         1.7,              0.2,              \"texture\",                2.5,        1.0,      0,          0,          0,              0,              \"speed boat\"]",
  "boat motor":             "[\"boat\",           4,        0.1,      0,        0,            1,            0,          65535,    \"box\",    \"[1, 1]\",                                                                         0,            0,                0,                \"line loop\",              2.5,        1.0,      0,          0,          -2,             1,              \"body\"]",
  "boat prop":              "[\"boat prop\",      4,        0.1,      0,        0,            1,            0,          65535,    \"box\",    \"[0.2, 3]\",                                                                       0,            0,                0,                \"texture\",                2.5,        1.0,      0,          0,          0,              0,              \"ground\"]",
  "car":                    "[\"car\",            3,        0.1,      0,        0,            1,            0,          65535,    \"box\",    \"[5, 2]\",                                                                         0,            0,                0,                \"line loop\",              2.5,        1.0,      0,          0,          0,              0,              \"body\"]",
  "wheel1":                 "[\"wheel1\",         1,        10,       0,        0,            1,            0,          65535,    \"circle\", \"[1]\",                                                                            0,            0,                0,                \"texture\",                2.5,        1.0,      0,          0,          0,              0,              \"bucket ball\"]",
  "wheel2":                 "[\"wheel2\",         1,        10,       0,        0,            1,            0,          65535,    \"circle\", \"[1]\",                                                                            0,            0,                0,                \"texture\",                2.5,        1.0,      0,          0,          0,              0,              \"bucket ball\"]",
  "zero zero":              "[\"zero zero\",      1,        10,       0,        0,            1,            0,          65535,    \"sprite\", \"[1, 1]\",                                                                         5,            0,                0,                \"texture\",                2.5,        1.0,      0,          0,          0,              0,              \"zero zero\"]"
}